nissaga/__init__.py
nissaga/cli.py
nissaga/models.py
nissaga/models_test.py
nissaga/render.py
nissaga/render_test.py
nissaga/styles.py
nissaga/styles_test.py
nissaga-0.3.0.dist-info/LICENSE
nissaga-0.3.0.dist-info/METADATA
nissaga-0.3.0.dist-info/WHEEL
nissaga-0.3.0.dist-info/entry_points.txt
nissaga-0.3.0.dist-info/top_level.txt
nissaga-0.3.0.dist-info/RECORD
