Metadata-Version: 2.1
Name: nissaga
Version: 0.3.0
Summary: Generate family trees from genealogic information written in simple yaml format.
Home-page: https://github.com/vokimon/nissaga
Author: David García Garzón
Author-email: voki@canvoki.net
License: GNU Affero General Public License v3 or later (AGPLv3+)
Platform: UNKNOWN
Classifier: Programming Language :: Python
Classifier: Programming Language :: Python :: 3
Classifier: Topic :: Sociology :: Genealogy
Classifier: Intended Audience :: Developers
Classifier: Development Status :: 5 - Production/Stable
Classifier: License :: OSI Approved :: GNU Affero General Public License v3 or later (AGPLv3+)
Classifier: Operating System :: OS Independent
License-File: LICENSE
Requires-Dist: yamlns
Requires-Dist: pydantic
Requires-Dist: consolemsg
Requires-Dist: graphviz
